sgn/__init__.py
sgn/_version.py
sgn/apps.py
sgn/base.py
sgn/bottle.py
sgn/compose.py
sgn/control.py
sgn/frames.py
sgn/groups.py
sgn/logger.py
sgn/profile.py
sgn/py.typed
sgn/sinks.py
sgn/sources.py
sgn/subprocess.py
sgn/transforms.py
sgn/validator.py
sgn/visualize.py
sgn-0.5.0.dist-info/licenses/LICENSE
sgn-0.5.0.dist-info/METADATA
sgn-0.5.0.dist-info/WHEEL
sgn-0.5.0.dist-info/entry_points.txt
sgn-0.5.0.dist-info/top_level.txt
sgn-0.5.0.dist-info/RECORD
