Metadata-Version: 2.4
Name: sgn
Version: 0.5.0
Summary: A framework to help navigate buffers through a graph. The buffers must flow.
Author-email: Chad Hanna <crh184@psu.edu>, Yun-Jing Huang <yzh5436@psu.edu>, Jameson Rollins <jameson.rollins@ligo.org>, Patrick Godwin <partick.godwin@ligo.org>, James Kennington <jwkennington@psu.edu>
License: MPL-2.0
Project-URL: Homepage, https://git.ligo.org/greg/sgn
Project-URL: Documentation, https://greg.docs.ligo.org/sgn
Project-URL: Issues, https://git.ligo.org/greg/sgn/issues
Classifier: Programming Language :: Python :: 3
Classifier: License :: OSI Approved :: Mozilla Public License 2.0 (MPL 2.0)
Classifier: Operating System :: OS Independent
Requires-Python: >=3.10
License-File: LICENSE
Provides-Extra: bottle
Requires-Dist: bottle; extra == "bottle"
Provides-Extra: inspect
Requires-Dist: sgn-inspect; extra == "inspect"
Provides-Extra: monitoring
Requires-Dist: psutil; extra == "monitoring"
Provides-Extra: visualize
Requires-Dist: graphviz; extra == "visualize"
Provides-Extra: all
Requires-Dist: sgn[bottle]; extra == "all"
Requires-Dist: sgn[inspect]; extra == "all"
Requires-Dist: sgn[monitoring]; extra == "all"
Requires-Dist: sgn[visualize]; extra == "all"
Provides-Extra: test
Requires-Dist: sgn[all]; extra == "test"
Requires-Dist: numpy; extra == "test"
Requires-Dist: pytest; extra == "test"
Requires-Dist: pytest-cov; extra == "test"
Requires-Dist: pytest-markdown-docs; extra == "test"
Provides-Extra: docs
Requires-Dist: mkdocs; extra == "docs"
Requires-Dist: mkdocstrings; extra == "docs"
Requires-Dist: mkdocstrings-python; extra == "docs"
Requires-Dist: mkdocs-material; extra == "docs"
Requires-Dist: pymdown-extensions; extra == "docs"
Provides-Extra: lint
Requires-Dist: black; extra == "lint"
Requires-Dist: flake8; extra == "lint"
Requires-Dist: flake8-bandit; extra == "lint"
Requires-Dist: flake8-black; extra == "lint"
Requires-Dist: flake8-bugbear; extra == "lint"
Requires-Dist: flake8-future-annotations; extra == "lint"
Requires-Dist: flake8-isort; extra == "lint"
Requires-Dist: flake8-logging-format; extra == "lint"
Requires-Dist: flake8-pyproject; extra == "lint"
Requires-Dist: isort; extra == "lint"
Requires-Dist: mypy; extra == "lint"
Requires-Dist: mypy-extensions; extra == "lint"
Requires-Dist: typing_extensions; extra == "lint"
Provides-Extra: dev
Requires-Dist: sgn[docs]; extra == "dev"
Requires-Dist: sgn[lint]; extra == "dev"
Requires-Dist: sgn[monitoring]; extra == "dev"
Requires-Dist: sgn[test]; extra == "dev"
Dynamic: license-file
